pwdhash.py
pwdhash-0.2.0.dist-info/LICENSE
pwdhash-0.2.0.dist-info/METADATA
pwdhash-0.2.0.dist-info/WHEEL
pwdhash-0.2.0.dist-info/entry_points.txt
pwdhash-0.2.0.dist-info/top_level.txt
pwdhash-0.2.0.dist-info/RECORD
