Metadata-Version: 2.1
Name: pwdhash
Version: 0.2.0
Summary: A python implementation of PwdHash 1 and 2
Home-page: https://github.com/EricDuminil/pwdhash-py
Author: Eric Duminil
Author-email: pwdhash@ericduminil.com
Project-URL: Bug Tracker, https://github.com/EricDuminil/pwdhash-py
Classifier: Programming Language :: Python :: 3
Classifier: License :: OSI Approved :: MIT License
Classifier: Operating System :: OS Independent
Requires-Python: >=3.7
License-File: LICENSE
